README.rst
decode_image.py
setup.cfg
setup.py
decode_image/__init__.py
decode_image/clip.py
decode_image/decode.py
decode_image/decode_image.py
decode_image/encode.py
decode_image.egg-info/PKG-INFO
decode_image.egg-info/SOURCES.txt
decode_image.egg-info/dependency_links.txt
decode_image.egg-info/entry_points.txt
decode_image.egg-info/not-zip-safe
decode_image.egg-info/top_level.txt